segmentation_models_pytorch_3d/__init__.py
segmentation_models_pytorch_3d/__version__.py
segmentation_models_pytorch_3d/base/__init__.py
segmentation_models_pytorch_3d/base/heads.py
segmentation_models_pytorch_3d/base/initialization.py
segmentation_models_pytorch_3d/base/model.py
segmentation_models_pytorch_3d/base/modules.py
segmentation_models_pytorch_3d/datasets/__init__.py
segmentation_models_pytorch_3d/datasets/oxford_pet.py
segmentation_models_pytorch_3d/decoders/__init__.py
segmentation_models_pytorch_3d/decoders/deeplabv3/__init__.py
segmentation_models_pytorch_3d/decoders/deeplabv3/decoder.py
segmentation_models_pytorch_3d/decoders/deeplabv3/model.py
segmentation_models_pytorch_3d/decoders/fpn/__init__.py
segmentation_models_pytorch_3d/decoders/fpn/decoder.py
segmentation_models_pytorch_3d/decoders/fpn/model.py
segmentation_models_pytorch_3d/decoders/linknet/__init__.py
segmentation_models_pytorch_3d/decoders/linknet/decoder.py
segmentation_models_pytorch_3d/decoders/linknet/model.py
segmentation_models_pytorch_3d/decoders/manet/__init__.py
segmentation_models_pytorch_3d/decoders/manet/decoder.py
segmentation_models_pytorch_3d/decoders/manet/model.py
segmentation_models_pytorch_3d/decoders/pan/__init__.py
segmentation_models_pytorch_3d/decoders/pan/decoder.py
segmentation_models_pytorch_3d/decoders/pan/model.py
segmentation_models_pytorch_3d/decoders/pspnet/__init__.py
segmentation_models_pytorch_3d/decoders/pspnet/decoder.py
segmentation_models_pytorch_3d/decoders/pspnet/model.py
segmentation_models_pytorch_3d/decoders/unet/__init__.py
segmentation_models_pytorch_3d/decoders/unet/decoder.py
segmentation_models_pytorch_3d/decoders/unet/model.py
segmentation_models_pytorch_3d/decoders/unetplusplus/__init__.py
segmentation_models_pytorch_3d/decoders/unetplusplus/decoder.py
segmentation_models_pytorch_3d/decoders/unetplusplus/model.py
segmentation_models_pytorch_3d/encoders/__init__.py
segmentation_models_pytorch_3d/encoders/_base.py
segmentation_models_pytorch_3d-1.0.2.dist-info/LICENSE
segmentation_models_pytorch_3d-1.0.2.dist-info/METADATA
segmentation_models_pytorch_3d-1.0.2.dist-info/WHEEL
segmentation_models_pytorch_3d-1.0.2.dist-info/top_level.txt
segmentation_models_pytorch_3d-1.0.2.dist-info/RECORD
